[{"My Team Name":"Delhi Capitals","Opponent Team Name":"Mumbai Indians","Runs":"","Balls":"","4s":"","6s":"","SR":"","Date":" Nov 5 2020","Venue":" Dubai","Result":"Mum Indians won by 57 runs"},{"My Team Name":"Delhi Capitals","Opponent Team Name":"Mumbai Indians","Runs":"","Balls":"","4s":"","6s":"","SR":"","Date":" Nov 5 2020","Venue":" Dubai","Result":"Mum Indians won by 57 runs"},{"My Team Name":"Delhi Capitals","Opponent Team Name":"Mumbai Indians","Runs":"","Balls":"","4s":"","6s":"","SR":"","Date":" Nov 5 2020","Venue":" Dubai","Result":"Mum Indians won by 57 runs"},{"My Team Name":"Delhi Capitals","Opponent Team Name":"Mumbai Indians","Runs":"","Balls":"","4s":"","6s":"","SR":"","Date":" Nov 5 2020","Venue":" Dubai","Result":"Mum Indians won by 57 runs"},{"My Team Name":"Delhi Capitals","Opponent Team Name":"Mumbai Indians","Runs":"","Balls":"","4s":"","6s":"","SR":"","Date":" Nov 5 2020","Venue":" Dubai","Result":"Mum Indians won by 57 runs"},{"My Team Name":"Delhi Capitals","Opponent Team Name":"Mumbai Indians","Runs":"","Balls":"","4s":"","6s":"","SR":"","Date":" Nov 5 2020","Venue":" Dubai","Result":"Mum Indians won by 57 runs"}]